renderer/__init__.py
renderer/bridge.py
renderer/bridge_context.py
renderer/serializer.py
renderer/settings.py
renderer/slog.py
renderer/examples/locale.json
renderer/examples/structlog.txt
renderer/examples/test.json
renderer/examples/unicode.txt
renderer/examples/urdu.json
renderer-1.0.2.dist-info/DESCRIPTION.rst
renderer-1.0.2.dist-info/METADATA
renderer-1.0.2.dist-info/RECORD
renderer-1.0.2.dist-info/WHEEL
renderer-1.0.2.dist-info/metadata.json
renderer-1.0.2.dist-info/top_level.txt
